{
    "companies": [
      {
        "name": "Lakeview Center, Inc",
        "address": "1221 W. Lakeview Ave., Pensacola, FL 32501",
        "phone": "(850)432-122",
        "url": "https://www.elakeviewcenter.org/",
        "membership": "Gold",
        "imageurl": "./images/Lakeview.png"},
      {
        "name": "Community Health Northwest Florida",
        "address": "2315 W. Jackson St, Pensacola, FL 32501",
        "phone": "(850)436-4630",
        "url": "https://healthcarewithinreach.org/",
        "membership": "Gold",
        "imageurl": "./images/community_health.png"},
      {
       "name": "Home Instead",
        "address": "817 N. Palafox St., Pensacola, FL 32501",
        "phone": "(850)477-1947",
        "url": "https://www.homeinstead.com/",
        "membership": "Silver",
        "imageurl": "./images/home_instead.png"},

      {
        "name": "Pensacola Interstate Fair, Inc.",
        "address": "6655 Mobile Hwy., Pensacola, FL 32501",
        "phone": "(850)944-4500",
        "url": "http://www.pensacolafair.com/",
        "membership": "Bronze",
        "imageurl": "./images/interstate_fair.png"},

      {
        "name": "Flora-Bama Marina",
        "address": "29603 Perdido Beach Blvd., Orange Beach, AL, 36561",
        "phone": "(251)980-5222",
        "url": "https://www.fishflorabama.com/",
        "membership": "Silver",
        "imageurl": "./images/marina.png"},

      {
        "name": "Pensacola Blue Wahoos",
        "address": "351 W. Cedar St., Pensacola, FL 32502",
        "phone": "(850)934-8444",
        "url": "https://www.milb.com/pensacola",
        "membership": "Gold",
        "imageurl": "./images/wahoos.png"},

      {
        "name": "Laguna's Beach Bar + Grill",
        "address": "460 Pensacola Beach Blvd., Pensacola, FL 32561",
        "phone": "(850)677-3905",
        "url": "https://lagunaspensacolabeach.com/",
        "membership": "Silver",
        "imageurl": "./images/grill.png"},

      {
        "name": "Crabs - We got 'em",
        "address": "6 Casino Beach Boardwalk,, Pensacola, FL 32561",
        "phone": "(850)434-8364",
        "url": "https://crabsonthebeach.com/",
        "membership": "Bronze",
        "imageurl": "./images/crab.png"},

      {
        "name": "Blue Moon Antique Mall",
        "address": "3721 W. Navy Blvd., Pensacola, FL 32507",
        "phone": "(850)455-7377",
        "url": "https://www.zaful.com/?lkid=82643924&subid=43e8b35755a7d6d925f220587960efc1",
        "membership": "Bronze",
        "imageurl": "./images/mall.png"}
          
    ]}